{
  "name": "ColorSimulatorRojo",
  "tree": {
    "$className": "DataModel",

    "ReplicatedStorage": {
      "ColorData": {
        "$path": "src/shared/ColorData.luau"
      },
      "CodeData": {
        "$path": "src/shared/CodeData.luau"
      },
      "GameBalance": {
        "$path": "src/shared/GameBalance.luau"
      },
      "GroupRewardsConfig": {
        "$path": "src/shared/GroupRewardsConfig.luau"
      },
      "HUDAssetConfig": {
        "$path": "src/shared/HUDAssetConfig.luau"
      },
      "InventoryIconConfig": {
        "$path": "src/shared/InventoryIconConfig.luau"
      },
      "GamepassIconConfig": {
        "$path": "src/shared/GamepassIconConfig.luau"
      },
      "LightingConfig": {
        "$path": "src/shared/LightingConfig.luau"
      },
      "LightingPresets": {
        "$path": "src/shared/LightingPresets.luau"
      },
      "PhysicalMenuUIBuilder": {
        "$path": "src/shared/PhysicalMenuUIBuilder.luau"
      },
      "PhysicalCurrencyHUDBuilder": {
        "$path": "src/shared/PhysicalCurrencyHUDBuilder.luau"
      },
      "SettingsData": {
        "$path": "src/shared/SettingsData.luau"
      },
      "ToolData": {
        "$path": "src/shared/ToolData.luau"
      },
      "BrushData": {
        "$path": "src/shared/BrushData.luau"
      },
      "ItemsData": {
        "$path": "src/shared/ItemsData.luau"
      },
      "PetData": {
        "$path": "src/shared/PetData.luau"
      },
      "ColorPersonalityData": {
        "$path": "src/shared/ColorPersonalityData.luau"
      },
      "ColorTraitData": {
        "$path": "src/shared/ColorTraitData.luau"
      },
      "ColorMutationData": {
        "$path": "src/shared/ColorMutationData.luau"
      },
      "RobuxShopConfig": {
        "$path": "src/shared/RobuxShopConfig.luau"
      },
      "AdminConfig": {
        "$path": "src/shared/AdminConfig.luau"
      },
      "AudioIds": {
        "$path": "src/shared/AudioIds.luau"
      },
      "VFXConfig": {
        "$path": "src/shared/VFXConfig.luau"
      },
      "UpdateLogData": {
        "$path": "src/shared/UpdateLogData.luau"
      },
      "StudioZoneBuilder": {
        "$path": "src/shared/StudioZoneBuilder.luau"
      },
      "StudioPetAppearanceBuilder": {
        "$path": "src/shared/StudioPetAppearanceBuilder.luau"
      },
      "StudioSectorInteriorBuilder": {
        "$path": "src/shared/StudioSectorInteriorBuilder.luau"
      },
      "StudioMapCleaner": {
        "$path": "src/shared/StudioMapCleaner.luau"
      },
      "StudioMenuWindowsBuilder": {
        "$path": "src/shared/StudioMenuWindowsBuilder.luau"
      },
      "StudioZorkWindowsUpdater": {
        "$path": "src/shared/StudioZorkWindowsUpdater.luau"
      },
      "StudioEggPromptBuilder": {
        "$path": "src/shared/StudioEggPromptBuilder.luau"
      },
      "UIManager": {
        "$path": "src/shared/UIManager.luau"
      },
      "ClientUIRoot": {
        "$path": "src/shared/ClientUIRoot.luau"
      },
      "UITheme": {
        "$path": "src/shared/UITheme.luau"
      },
      "UpgradeData": {
        "$path": "src/shared/UpgradeData.luau"
      },
      "UpgradeIconConfig": {
        "$path": "src/shared/UpgradeIconConfig.luau"
      },

      "Modules": {
        "$className": "Folder",
        "PetTraits": {
          "$path": "src/modules/PetTraits.luau"
        },
        "PetDefinitions": {
          "$path": "src/modules/PetDefinitions.luau"
        },
        "PetModelUtil": {
          "$path": "src/modules/PetModelUtil.luau"
        },
        "LegendaryColorOrbDefinitions": {
          "$path": "src/modules/LegendaryColorOrbDefinitions.luau"
        },
        "LegendaryColorOrbBuilder": {
          "$path": "src/modules/LegendaryColorOrbBuilder.luau"
        }
      },

      "PetModels": {
        "$className": "Folder"
      },

      "Events": {
        "$className": "Folder",
        "CollectColor": {
          "$className": "RemoteEvent"
        },
        "PaintToolSweep": {
          "$className": "RemoteEvent"
        },
        "ColorEffectVFX": {
          "$className": "RemoteEvent"
        },
        "HatchEgg": {
          "$className": "RemoteEvent"
        },
        "EquipPet": {
          "$className": "RemoteEvent"
        },
        "LockPet": {
          "$className": "RemoteEvent"
        },
        "DeletePet": {
          "$className": "RemoteEvent"
        },
        "MergePet": {
          "$className": "RemoteEvent"
        },
        "PetAttack": {
          "$className": "RemoteEvent"
        },
        "PetsLoaded": {
          "$className": "RemoteEvent"
        },
        "PurchaseUpgrade": {
          "$className": "RemoteEvent"
        },
        "UnlockArea": {
          "$className": "RemoteEvent"
        },
        "RequestTravelToSector": {
          "$className": "RemoteEvent"
        },
        "TravelToMarket": {
          "$className": "RemoteEvent"
        },
        "TravelToWorldSpot": {
          "$className": "RemoteEvent"
        },
        "TeleportToSell": {
          "$className": "RemoteEvent"
        },
        "SellColor": {
          "$className": "RemoteEvent"
        },
        "RedeemCode": {
          "$className": "RemoteEvent"
        },
        "DevGrantCoins": {
          "$className": "RemoteEvent"
        },
        "UseItem": {
          "$className": "RemoteEvent"
        },
        "PurchasePaintTool": {
          "$className": "RemoteEvent"
        },
        "EquipPaintTool": {
          "$className": "RemoteEvent"
        },
        "RequestSetSetting": {
          "$className": "RemoteEvent"
        },
        "SettingsUpdated": {
          "$className": "RemoteEvent"
        },
        "GroupRewards": {
          "$className": "RemoteEvent"
        },
        "MutationStation": {
          "$className": "RemoteEvent"
        }
      },

      "Remotes": {
        "$className": "Folder",
        "InventoryRequest": {
          "$className": "RemoteFunction"
        },
        "InventoryAction": {
          "$className": "RemoteEvent"
        },
        "TradeRequest": {
          "$className": "RemoteFunction"
        },
        "TradeUpdate": {
          "$className": "RemoteEvent"
        }
      }
    },

    "ServerScriptService": {
      "AAA_DisableRuntimeItemGrants": {
        "$path": "src/server_root/AAA_DisableRuntimeItemGrants.server.luau"
      },
      "Server": {
        "$path": "src/server"
      }
    },

    "StarterGui": {
      "$className": "StarterGui",
      "$ignoreUnknownInstances": true,

      "LoadingGui": {
        "$className": "ScreenGui",
        "$properties": {
          "DisplayOrder": 100000,
          "Enabled": true,
          "IgnoreGuiInset": true,
          "ResetOnSpawn": false,
          "ZIndexBehavior": "Sibling",
          "Attributes": {
            "ColorSimulatorLoadingGui": {
              "Bool": true
            }
          }
        },

        "LoadingRoot": {
          "$className": "Frame",
          "$properties": {
            "BackgroundColor3": [0.011765, 0.015686, 0.027451],
            "BorderSizePixel": 0,
            "Position": {
              "UDim2": [[0, 0], [0, 0]]
            },
            "Size": {
              "UDim2": [[1, 0], [1, 0]]
            },
            "ZIndex": 1
          },

          "TopGlow": {
            "$className": "Frame",
            "$properties": {
              "BackgroundColor3": [0.098039, 0.870588, 1],
              "BackgroundTransparency": 0.35,
              "BorderSizePixel": 0,
              "Position": {
                "UDim2": [[0, 0], [0, 0]]
              },
              "Size": {
                "UDim2": [[1, 0], [0, 4]]
              },
              "ZIndex": 2
            }
          },

          "BottomGlow": {
            "$className": "Frame",
            "$properties": {
              "BackgroundColor3": [1, 0.215686, 0.517647],
              "BackgroundTransparency": 0.4,
              "BorderSizePixel": 0,
              "Position": {
                "UDim2": [[0, 0], [1, -5]]
              },
              "Size": {
                "UDim2": [[1, 0], [0, 5]]
              },
              "ZIndex": 2
            }
          },

          "Panel": {
            "$className": "Frame",
            "$properties": {
              "AnchorPoint": [0.5, 0.5],
              "BackgroundColor3": [0.027451, 0.035294, 0.058824],
              "BorderSizePixel": 0,
              "Position": {
                "UDim2": [[0.5, 0], [0.5, 0]]
              },
              "Size": {
                "UDim2": [[0.62, 0], [0, 230]]
              },
              "ZIndex": 10
            },

            "PanelSizeLimit": {
              "$className": "UISizeConstraint",
              "$properties": {
                "MaxSize": [680, 260],
                "MinSize": [320, 210]
              }
            },

            "Corner": {
              "$className": "UICorner",
              "$properties": {
                "CornerRadius": {
                  "UDim": [0, 8]
                }
              }
            },

            "Stroke": {
              "$className": "UIStroke",
              "$properties": {
                "Color": [0.098039, 0.870588, 1],
                "Thickness": 2,
                "Transparency": 0.1
              }
            },

            "AccentLeft": {
              "$className": "Frame",
              "$properties": {
                "BackgroundColor3": [1, 0.215686, 0.517647],
                "BorderSizePixel": 0,
                "Position": {
                  "UDim2": [[0, 0], [0, 0]]
                },
                "Size": {
                  "UDim2": [[0, 5], [1, 0]]
                },
                "ZIndex": 12
              }
            },

            "AccentRight": {
              "$className": "Frame",
              "$properties": {
                "BackgroundColor3": [0.521569, 1, 0.231373],
                "BorderSizePixel": 0,
                "Position": {
                  "UDim2": [[1, -5], [0, 0]]
                },
                "Size": {
                  "UDim2": [[0, 5], [1, 0]]
                },
                "ZIndex": 12
              }
            },

            "Title": {
              "$className": "TextLabel",
              "$properties": {
                "BackgroundTransparency": 1,
                "Font": "GothamBlack",
                "Position": {
                  "UDim2": [[0, 28], [0, 34]]
                },
                "Size": {
                  "UDim2": [[1, -56], [0, 54]]
                },
                "Text": "Loading Color Simulator...",
                "TextColor3": [1, 1, 1],
                "TextScaled": true,
                "TextXAlignment": "Center",
                "TextYAlignment": "Center",
                "ZIndex": 14
              },

              "TextSizeLimit": {
                "$className": "UITextSizeConstraint",
                "$properties": {
                  "MaxTextSize": 34,
                  "MinTextSize": 18
                }
              }
            },

            "StatusText": {
              "$className": "TextLabel",
              "$properties": {
                "BackgroundTransparency": 1,
                "Font": "GothamBold",
                "Position": {
                  "UDim2": [[0, 34], [0, 104]]
                },
                "Size": {
                  "UDim2": [[1, -68], [0, 34]]
                },
                "Text": "Loading data...",
                "TextColor3": [0.760784, 0.878431, 1],
                "TextScaled": true,
                "TextXAlignment": "Center",
                "TextYAlignment": "Center",
                "ZIndex": 14
              },

              "TextSizeLimit": {
                "$className": "UITextSizeConstraint",
                "$properties": {
                  "MaxTextSize": 20,
                  "MinTextSize": 12
                }
              }
            },

            "ProgressBack": {
              "$className": "Frame",
              "$properties": {
                "BackgroundColor3": [0.007843, 0.011765, 0.019608],
                "BorderSizePixel": 0,
                "Position": {
                  "UDim2": [[0, 44], [1, -70]]
                },
                "Size": {
                  "UDim2": [[1, -88], [0, 12]]
                },
                "ZIndex": 14
              },

              "Corner": {
                "$className": "UICorner",
                "$properties": {
                  "CornerRadius": {
                    "UDim": [1, 0]
                  }
                }
              },

              "Stroke": {
                "$className": "UIStroke",
                "$properties": {
                  "Color": [0.196078, 0.266667, 0.403922],
                  "Thickness": 1,
                  "Transparency": 0.15
                }
              },

              "ProgressFill": {
                "$className": "Frame",
                "$properties": {
                  "BackgroundColor3": [0.098039, 0.870588, 1],
                  "BorderSizePixel": 0,
                  "Position": {
                    "UDim2": [[0, 0], [0, 0]]
                  },
                  "Size": {
                    "UDim2": [[0.1, 0], [1, 0]]
                  },
                  "ZIndex": 15
                },

                "Corner": {
                  "$className": "UICorner",
                  "$properties": {
                    "CornerRadius": {
                      "UDim": [1, 0]
                    }
                  }
                }
              }
            },

            "SectorText": {
              "$className": "TextLabel",
              "$properties": {
                "BackgroundTransparency": 1,
                "Font": "Gotham",
                "Position": {
                  "UDim2": [[0, 34], [1, -44]]
                },
                "Size": {
                  "UDim2": [[1, -68], [0, 22]]
                },
                "Text": "Sector systems online",
                "TextColor3": [0.521569, 1, 0.231373],
                "TextScaled": true,
                "TextTransparency": 0.25,
                "TextXAlignment": "Center",
                "TextYAlignment": "Center",
                "ZIndex": 14
              },

              "TextSizeLimit": {
                "$className": "UITextSizeConstraint",
                "$properties": {
                  "MaxTextSize": 14,
                  "MinTextSize": 10
                }
              }
            }
          }
        }
      },

      "TutorialGui": {
        "$path": "src/startergui/TutorialGui.model.json"
      }
    },

    "StarterPlayer": {
      "StarterPlayerScripts": {
        "Client": {
          "$path": "src/client"
        }
      }
    }
  }
}
